<?xml version="1.0" encoding="UTF-8" ?>
<ApplicationManifest xmlns="http://schemas.google.com/ApplicationManifest/2009">

  <!-- Support info to show in the marketplace & control panel -->
  <Support>
    <!-- URL for application setup as an optional redirect during the install -->
    <Link rel="setup" href="http://widgit.tk/piu-piu/" />

    <!-- URL for application configuration, accessed from the app settings page in the control panel -->
    <Link rel="manage" href="http://widgit.tk/piu-piu/" />

    <!-- URL explaining how customers get support. -->
    <Link rel="support" href="http://widgit.tk/piu-piu/#support" />

    <!-- URL that is displayed to admins during the deletion process, to specify policies such as data retention, how to claim accounts, etc. -->
    <Link rel="deletion-policy" href="http://widgit.tk/piu-piu/#policy" />
  </Support>

  <!-- Name and description pulled from message bundles -->
  <Name>piu-piu</Name>
  <Description>Chirp text, images and URLs from your Chrome Browser.</Description>

  <!-- Show this link in Google's universal navigation for all users -->
  <Extension id="navLink" type="link">
    <Name>piu-piu</Name>
    <Url>http://widgit.tk/piu-piu/</Url>
    <!-- NO API at all -->
    <!--<Scope ref="" />-->
  </Extension>

  <!-- Declare our OpenID realm so our app is white listed -->
  <Extension id="realm" type="openIdRealm">
    <Url>http://widgit.tk</Url>
  </Extension>

  <!-- NO Scope at all -->
  <!--<Scope id="">
    <Url>http:///</Url>
    <Reason>NONE</Reason>
  </Scope>-->

</ApplicationManifest>